contribution/__init__.py
contribution/admin.py
contribution/apps.py
contribution/gql_mutations.py
contribution/gql_queries.py
contribution/models.py
contribution/report.py
contribution/schema.py
contribution/services.py
contribution/test_helpers.py
contribution/tests.py
contribution/tests_gql.py
contribution/urls.py
contribution/utils.py
contribution/views.py
contribution/migrations/0001_initial.py
contribution/migrations/0002_add_premium_fields.py
contribution/migrations/0003_alter_premium_options.py
contribution/migrations/0004_auto_20230718_1155.py
contribution/migrations/0005_alter_created_date.py
contribution/migrations/0006_add_source_field_to_contribution.py
contribution/migrations/0007_add_missing_fields_not_mssql.py
contribution/migrations/0008_alter_psql_created_date.py
contribution/migrations/__init__.py
contribution/reports/__init__.py
contribution/reports/contributions_distribution.py
contribution/reports/payment_category_overview.py
contribution/reports/premium_collection.py
openimis_be_contribution-1.9.1.dist-info/licenses/LICENSE.md
openimis_be_contribution-1.9.1.dist-info/METADATA
openimis_be_contribution-1.9.1.dist-info/WHEEL
openimis_be_contribution-1.9.1.dist-info/top_level.txt
openimis_be_contribution-1.9.1.dist-info/RECORD
